octoclient/__init__.py
octoclient/client.py
octoclient/sockjsclient.py
octoclient/websocket.py
octoclient/xhrstreaming.py
octoclient/xhrstreaminggenerator.py
octoclient-0.2.dev1.dist-info/DESCRIPTION.rst
octoclient-0.2.dev1.dist-info/METADATA
octoclient-0.2.dev1.dist-info/RECORD
octoclient-0.2.dev1.dist-info/WHEEL
octoclient-0.2.dev1.dist-info/metadata.json
octoclient-0.2.dev1.dist-info/top_level.txt
